codaio/__init__.py
codaio/coda.py
codaio/err.py
codaio-0.6.11.dist-info/LICENSE
codaio-0.6.11.dist-info/METADATA
codaio-0.6.11.dist-info/WHEEL
codaio-0.6.11.dist-info/RECORD
