Metadata-Version: 2.1
Name: codaio
Version: 0.6.11
Summary: Python wrapper for Coda.io API
Home-page: https://github.com/Blasterai/codaio
License: MIT
Author: MB
Author-email: mb@blaster.ai
Requires-Python: >=3.9,<4.0
Classifier: License :: OSI Approved :: MIT License
Classifier: Programming Language :: Python :: 3
Classifier: Programming Language :: Python :: 3.9
Classifier: Programming Language :: Python :: 3.10
Classifier: Programming Language :: Python :: 3.11
Requires-Dist: attrs (>=23.1.0,<24.0.0)
Requires-Dist: decorator (>=5.1.1,<6.0.0)
Requires-Dist: envparse (>=0.2.0,<0.3.0)
Requires-Dist: inflection (>=0.5.1,<0.6.0)
Requires-Dist: python-dateutil (>=2.8.2,<3.0.0)
Requires-Dist: requests (>=2.31.0,<3.0.0)
Project-URL: Documentation, https://codaio.readthedocs.io/en/latest/index.html
